{"summary":{"AutomatchType":0,"Abroad":false,"Weight":1,"Title":"Skovvænget søger relations medarbejdere - løbende ansættelser","JobHeadline":"Skovvænget søger relations medarbejdere - løbende ansættelser","Presentation":"Skovvænget søger relations medarbejdere – løbende ansættelser                                                                                                                          ","HiringOrgName":"Skovvænget","WorkPlaceAddress":"Ballerup Boulevard 2","WorkPlacePostalCode":"2750","WorkPlaceCity":"Ballerup","WorkPlaceOtherAddress":false,"WorkPlaceAbroad":false,"WorkPlaceNotStatic":false,"UseWorkPlaceAddressForJoblog":true,"PostingCreated":"2022-04-04T00:00:00","LastDateApplication":"2022-05-30T00:00:00","FormattedLastDateApplication":"30. maj 2022","AssignmentStartDate":"0001-01-01T00:00:00","IsHotjob":false,"IsExternal":false,"Url":"https://job.jobnet.dk/CV/FindWork/Details/5297058","Region":"Hovedstaden og Bornholm","Municipality":"Ballerup","Country":"Danmark","PostalCode":"2750","PostalCodeName":null,"JobAnnouncementType":"","EmploymentType":"","WorkHours":"Fuldtid","OccupationArea":"Sundhed, omsorg og personlig pleje","OccupationGroup":"Pleje og omsorg","Occupation":"Social- og sundhedsassistent","Location":{"Latitude":55.7367,"Longitude":12.3638},"JoblogWorkTime":{"WorkHour":null,"DailyWorkTime":null},"WorkplaceID":108633,"OrganisationId":"58913","HiringOrgCVR":29190623,"UserLoggedIn":false,"AnonymousEmployer":false,"ShareUrl":"https://job.jobnet.dk/CV/FindWork/DetailsSocialmedia/5297058","DetailsUrl":"https://job.jobnet.dk/CV/FindWork/Details/5297058","JobLogUrl":"https://job.jobnet.dk/CV/FindWork/Details/5297058","HasLocationValues":true,"ID":"5297058","Latitude":55.7367,"Longitude":12.3638},"details":{"WorkSchedule":[{"Id":1,"Name":"Fuldtid"},{"Id":16,"Name":"Deltid"}],"WorkConditions":[{"Id":1,"Name":"Almindelige vilkår"},{"Id":2,"Name":"Fleksjob"},{"Id":3,"Name":"Skånejob"},{"Id":4,"Name":"Egnet til efterlønnere og seniorer"},{"Id":5,"Name":"Job med løntilskud"},{"Id":6,"Name":"Rotationsjob"},{"Id":7,"Name":"Virksomhedspraktik"}],"EmploymentTypes":[{"Id":1,"Name":"Fastansættelse"},{"Id":16,"Name":"Tidsbegrænset ansættelse"}],"WorkPlace":{"Name":"Skovvænget","Address":{"AddressLine":"Ballerup Boulevard 2","Country":{"Id":58,"Name":"Danmark"},"Municipality":{"Id":151,"Name":"Ballerup"},"Region":{"Id":4,"Name":"Hovedstaden, Sjælland og Bornholm"},"PostalCode":"2750","City":"Ballerup"},"PhoneNumber":{"Number":"29785999","Type":0,"Description":"Primary"},"FaxNumber":null,"Email":null,"WebAddress":null,"Description":null,"Logo":108633,"WorkPlaceOrganizationNumber":"1003258551","OrganizationNumber":"29190623","OrganizationDescription":null},"JobPositionPosting":{"Id":5297058,"OriginalJppId":5297058,"HiringOrg":{"Name":"Skovvænget","Address":{"AddressLine":"Ballerup Boulevard 2","Country":{"Id":58,"Name":"Danmark"},"Municipality":{"Id":151,"Name":"Ballerup"},"Region":{"Id":4,"Name":"Hovedstaden, Sjælland og Bornholm"},"PostalCode":"2750","City":"Ballerup"},"PhoneNumber":{"Number":"29785999","Type":0,"Description":"Primary"},"FaxNumber":null,"Email":null,"WebAddress":null,"Description":null,"Logo":108633,"WorkPlaceOrganizationNumber":"1003258551","OrganizationNumber":"29190623","OrganizationDescription":null},"RecruitingCompany":null,"PublicationStartDate":"2022-04-04T00:00:00","PublicationEndDate":"2022-05-30T00:00:00","JobPositionInformation":{"PositionTitle":"Skovvænget søger relations medarbejdere - løbende ansættelser","Purpose":"<strong>Skovvænget søger relations medarbejdere – løbende ansættelser</strong>                                                                                                                                                                                                                                                                 <br><br>  Mener du også at dialog og nærvær er det vigtigste udgangspunkt for det gode samarbejde med borgerne? Så skal du søge én af vores stillinger.<br><br>  Skovvænget er et socialpsykiatrisk special tilbud under Region Hovedstaden. Den Sociale Virksomhed.<br><br>  Finder du det inspirerende at tale med mennesker, vil du få rig mulighed for dette i vores Åben Dialog samtaler med borgerne.  Er du samtidig til fisketure, en fodboldkamp, musik eller hygge i vores Café så læs videre her.<br><br>  Skovvænget tilbyder indsatser efter Servicelovens §§107,108 for voksne med komplekse psykiske- og sociale problemer, ofte inklusive et rusmiddelbrug.<br><br>  Vi ønsker stor mangfoldighed i medarbejdergruppen. Vi opfordrer både nyuddannede og erfarne fagpersoner i alle aldersgrupper til at søge stillingerne. Vi anser bruger baggrund som en særlig kvalifikation. Vi er en meget engageret tværfaglig sammensat medarbejdergruppe, der søger nye gode kollegaer.<br><br>  Skovvængets faglige perspektiv er psykosocial rehabilitering, som understøtter den enkelte beboers recovery proces.<br><br>  Vi arbejder med en Åben Dialogisk- og netværksbaseret tilgang i et tværfagligt samarbejde og med beboeren i centrum.<br><br>  <ul> \t<li>Vi forventer at du er optaget af både de sociale- og sundhedsfaglige perspektiver i dit fag.</li> \t<li>Vi forventer at du er fagligt ambitiøs, da vi uddanner relations medarbejderne i Åben Dialog, Feedback Informed Treatment, (FIT), samt en række andre specialiserede fagmetoder.</li> \t<li>Vi forventer, at du har stor interesse i at indgå i tætte relationelle samarbejder, samt kan tage ansvar for udførelsen af kerneopgaverne.</li> \t<li>Vi forventer, at du har stor interesse i at udvikle din viden og kompetencer i et højt specialiseret fagligt felt, hvor du arbejder med komplekse opgaver.</li> </ul>  Vi er ca. 45 medarbejdere på Skovvænget og vi har 30 lejligheder fordelt på tre vinkelhuse.<br><br>  Skovvænget har en skøn Café, hvor vi spiser og hygger sammen med borgerne. Vi har et sanserum, lokaler hvor vi kan spille musik og holde netcafé. Vi har et lille drivhus og dejlige haver rundt om husene. Vi drømmer om at få udviklet noget af haven til sansehave. Er du til fysisk træning, så mød kollegaer og borgere i vores mellemstore fitnesscenter.<br><br>  Stillingerne er på 37 timer pr. uge, primært i dag- og aftentimerne, fordelt over ugens syv dage.<br><br>  Stillingerne ønskes besat hurtigst muligt<br><br>  Ansættelsessamtaler afholdes løbende<br><br>  <strong>Samtalerne afholdes i Skovvængets Administration, Maglevænget 48, 2750 Ballerup</strong><br><br>  Skovvængets hjemmeside: www.skovvænget.dk<br><br>  <strong>Kontaktpersoner: Mellemleder Elvira Vistisen: 29785999 og mellemleder Irene Koldtoft: 23260148</strong><br><br>   <br><br>","WorkLocation":{"AddressLine":"Ballerup Boulevard 2","Country":{"Id":58,"Name":"Danmark"},"Municipality":{"Id":151,"Name":"Ballerup"},"Region":{"Id":4,"Name":"Hovedstaden, Sjælland og Bornholm"},"PostalCode":"2750","City":"Ballerup"},"EmploymentType":1,"WeeklyWorkHours":{"TypeId":1,"TypeName":"Fuldtid","Description":null},"CompensationDescription":null,"NumberToFill":3,"DriverLicense":[],"Occupation":{"DiscoWeb":0,"AlternateNames":[],"GroupId":0,"AreaId":0,"Id":0,"Name":null},"IsGovernmentHiring":false,"JppContacts":[{"Id":7878102,"Email":null,"FaxNumber":null,"PersonName":"Elvira Vistisen","FirstName":"Elvira","LastName":"Vistisen","PositionTitle":"Mellemleder","PhoneNumbers":[{"Number":"29785999","Type":0,"Description":"Hovednummer"}]}],"EmploymentDate":null},"IsRecruitmentOfForeignNationals":false,"IsWorkInDenmark":false,"IsAnonymousEmployer":false,"IsDisabilityFriendly":false,"JppType":4,"ApplicationDetails":{"WorkHourMax":null,"WorkHourMin":null,"DailyWorkTimeWeekend":false,"DailyWorkTimeNight":false,"DailyWorkTimeEvening":false,"DailyWorkTimeDay":false,"ReferenceText":null,"RemarksToApplicant":null,"ByEmail":null,"ByPhone":null,"ApplyViaUrl":"https://candidate.hr-manager.net/ApplicationInit.aspx?cid=342&ProjectId=218849&DepartmentId=21807&MediaId=338&SkipAdvertisement=true","ReplyInWriting":false,"ApplicationDeadlineDate":"2022-05-30T00:00:00"},"ContactAuthorityPhoneNumber":{"Number":null,"Type":0,"Description":"Primary"},"Status":7},"LogoUrl":"/CV/FindWork/GetLogo?JobAdId=5297058&WorkPlace=108633&Organisation=29190623","Address":"Ballerup Boulevard 2,2750, Ballerup","ShowMap":true,"ShowShareButtonJobLog":false,"JobLogUrl":"/CV/Jobseeking/JobLog/CreateJobSearch?JobnetJobPostingIdentifier=5297058&Company.Name=Skovvænget&SubmissionDeadlineDate=2022-5-30&Title=Skovvænget søger relations medarbejdere - løbende ansættelser&WeeklyWorkTime=1","JobLogTemplateModel":{"Identifier":"00000000-0000-0000-0000-000000000000","UseWorkPlaceAddressForJoblog":false,"Category":0,"CvCustomerIdentifier":null,"JobSeekingStatus":null,"Title":"Skovvænget søger relations medarbejdere - løbende ansættelser","IsApplicationSourceRequired":true,"ApplicationSource":null,"IsWeeklyWorkTimeRequired":true,"WeeklyWorkTime":1,"HoursPerWeek":null,"JobnetJobPostingIdentifier":"5297058","JobAdDocument":{"Title":null,"Identifier":null,"IsDeletedBySystem":false,"IsDeletedByUser":false},"JobAdFile":null,"Company":{"JobLogEntryCategory":0,"ShowAddressFieldsEvenIfEmpty":false,"Name":"Skovvænget","Address":"Ballerup Boulevard 2","Country":null,"EmploymentAreaID":null,"PostCode":"2750","IsCountryAndTownAndPostCodeEmpty":false,"IsTownAndPostCodeEmpty":false,"IsCountryDanmark":false,"Town":"Ballerup","ContactPerson":"Elvira Vistisen","Phone":"29785999","Email":null,"Latitude":null,"Longitude":null,"DailyTravelTimeInMinutes":null,"DistanceToCompanyInMeters":null,"IsCreateMode":false},"TypeOfSubmission":null,"SubmissionDate":"2022-05-30T00:00:00","SubmissionDateFormatted":null,"SubmissionDateTiks":0,"IsSubmissionDateRequired":false,"Status":0,"DateCreatedFormatted":null,"DateCreated":null,"DateModifiedFormatted":null,"DateModified":null,"LastModifiedDateTiks":0,"DateClosed":null,"JobApplicationDocument":{"Title":null,"Identifier":null,"IsDeletedBySystem":false,"IsDeletedByUser":false},"CvDocument":{"Title":null,"Identifier":null,"IsDeletedBySystem":false,"IsDeletedByUser":false},"JobApplicationFile":null,"CvFile":null,"SubmissionDeadlineDate":null,"IsPersisted":false,"ServerValidationErrors":[],"HasServerValidationErrors":false},"JoblogWorkTime":{"WorkHour":null,"DailyWorkTime":null},"Place":"Arbejdspladsen ligger i Ballerup kommune","OpenPrintDialog":false,"WorkPlaceInfoText":"Skovvænget","JobCenterContactDetails":"","WorkPlaceDescriptionText":null,"FavoriteText":"","IsFavorite":false,"ShowFavorite":false,"MetaOgTextForSharing":"Skovvænget søger relations medarbejdere – løbende ansættelser                                                                                                                                                                                                                                                                   Mener du også at dialog og nær","DescriptionForSharing":"\"Skovvænget søger relations medarbejdere – løbende ansættelser                                                                                                                                                                                                                                                                   Mener du også at dialog og nær\"","TitleForSharing":"\"Skovvænget søger relations medarbejdere - løbende ansættelser\"","RutePlan":"https://www.google.dk/maps/dir//Ballerup+Boulevard+2,2750,+Ballerup/","FormattedPurpose":"<strong>Skovvænget søger relations medarbejdere – løbende ansættelser</strong>                                                                                                                                                                                                                                                                 <br><br>  Mener du også at dialog og nærvær er det vigtigste udgangspunkt for det gode samarbejde med borgerne? Så skal du søge én af vores stillinger.<br><br>  Skovvænget er et socialpsykiatrisk special tilbud under Region Hovedstaden. Den Sociale Virksomhed.<br><br>  Finder du det inspirerende at tale med mennesker, vil du få rig mulighed for dette i vores Åben Dialog samtaler med borgerne.  Er du samtidig til fisketure, en fodboldkamp, musik eller hygge i vores Café så læs videre her.<br><br>  Skovvænget tilbyder indsatser efter Servicelovens §§107,108 for voksne med komplekse psykiske- og sociale problemer, ofte inklusive et rusmiddelbrug.<br><br>  Vi ønsker stor mangfoldighed i medarbejdergruppen. Vi opfordrer både nyuddannede og erfarne fagpersoner i alle aldersgrupper til at søge stillingerne. Vi anser bruger baggrund som en særlig kvalifikation. Vi er en meget engageret tværfaglig sammensat medarbejdergruppe, der søger nye gode kollegaer.<br><br>  Skovvængets faglige perspektiv er psykosocial rehabilitering, som understøtter den enkelte beboers recovery proces.<br><br>  Vi arbejder med en Åben Dialogisk- og netværksbaseret tilgang i et tværfagligt samarbejde og med beboeren i centrum.<br><br>  <ul> \t<li>Vi forventer at du er optaget af både de sociale- og sundhedsfaglige perspektiver i dit fag.</li> \t<li>Vi forventer at du er fagligt ambitiøs, da vi uddanner relations medarbejderne i Åben Dialog, Feedback Informed Treatment, (FIT), samt en række andre specialiserede fagmetoder.</li> \t<li>Vi forventer, at du har stor interesse i at indgå i tætte relationelle samarbejder, samt kan tage ansvar for udførelsen af kerneopgaverne.</li> \t<li>Vi forventer, at du har stor interesse i at udvikle din viden og kompetencer i et højt specialiseret fagligt felt, hvor du arbejder med komplekse opgaver.</li> </ul>  Vi er ca. 45 medarbejdere på Skovvænget og vi har 30 lejligheder fordelt på tre vinkelhuse.<br><br>  Skovvænget har en skøn Café, hvor vi spiser og hygger sammen med borgerne. Vi har et sanserum, lokaler hvor vi kan spille musik og holde netcafé. Vi har et lille drivhus og dejlige haver rundt om husene. Vi drømmer om at få udviklet noget af haven til sansehave. Er du til fysisk træning, så mød kollegaer og borgere i vores mellemstore fitnesscenter.<br><br>  Stillingerne er på 37 timer pr. uge, primært i dag- og aftentimerne, fordelt over ugens syv dage.<br><br>  Stillingerne ønskes besat hurtigst muligt<br><br>  Ansættelsessamtaler afholdes løbende<br><br>  <strong>Samtalerne afholdes i Skovvængets Administration, Maglevænget 48, 2750 Ballerup</strong><br><br>  Skovvængets hjemmeside: <a target=\"_blank\" href=\"http://www.skovvænget.dk\" user-behavior-tracking=\"Contact\" user-behavior-tracking-id=\"5297058\">www.skovvænget.dk</a><br><br>  <strong>Kontaktpersoner: Mellemleder Elvira Vistisen: 29785999 og mellemleder Irene Koldtoft: 23260148</strong><br><br>   <br><br>","MapUrl":"https://www.google.dk/maps/place/Ballerup+Boulevard+2,2750,+Ballerup/","OrganizationNumber":"29190623","ShowSearchJobButton":false,"ShowPrint":false,"BackToFindWorkButtonUrl":null},"isExternal":false}