{"summary":{"AutomatchType":0,"Abroad":false,"Weight":1,"Title":"Vil du være med til at skabe Danmarks førende specialtilbud til udsatte børn og unge?","JobHeadline":"Vil du være med til at skabe Danmarks førende specialtilbud til udsatte børn og unge?","Presentation":"Trives du med at sætte trivsel og udvikling i centrum for dit arbejde ? Vil du understøtte det enkelte barns mulighed for et meningsfuldt liv ? Og kan du skabe struktur og forudsigelighed for børn","HiringOrgName":"Region Midtjylland","WorkPlaceAddress":"Strandvejen 24-26, Fjellerup","WorkPlacePostalCode":"8585","WorkPlaceCity":"Glesborg","WorkPlaceOtherAddress":false,"WorkPlaceAbroad":false,"WorkPlaceNotStatic":false,"UseWorkPlaceAddressForJoblog":true,"PostingCreated":"2022-04-06T00:00:00","LastDateApplication":"2022-05-25T00:00:00","FormattedLastDateApplication":"25. maj 2022","AssignmentStartDate":"0001-01-01T00:00:00","IsHotjob":false,"IsExternal":false,"Url":"https://job.jobnet.dk/CV/FindWork/Details/5571817","Region":"Midtjylland","Municipality":"Norddjurs","Country":"Danmark","PostalCode":"8585","PostalCodeName":null,"JobAnnouncementType":"","EmploymentType":"","WorkHours":"Fuldtid","OccupationArea":"Pædagogisk, socialt og kirkeligt arbejde","OccupationGroup":"Pædagogisk arbejde","Occupation":"Socialpædagog","Location":{"Latitude":56.5093,"Longitude":10.5912},"JoblogWorkTime":{"WorkHour":null,"DailyWorkTime":null},"WorkplaceID":0,"OrganisationId":"57696","HiringOrgCVR":29190925,"UserLoggedIn":false,"AnonymousEmployer":false,"ShareUrl":"https://job.jobnet.dk/CV/FindWork/DetailsSocialmedia/5571817","DetailsUrl":"https://job.jobnet.dk/CV/FindWork/Details/5571817","JobLogUrl":"https://job.jobnet.dk/CV/FindWork/Details/5571817","HasLocationValues":true,"ID":"5571817","Latitude":56.5093,"Longitude":10.5912},"details":{"WorkSchedule":[{"Id":1,"Name":"Fuldtid"},{"Id":16,"Name":"Deltid"}],"WorkConditions":[{"Id":1,"Name":"Almindelige vilkår"},{"Id":2,"Name":"Fleksjob"},{"Id":3,"Name":"Skånejob"},{"Id":4,"Name":"Egnet til efterlønnere og seniorer"},{"Id":5,"Name":"Job med løntilskud"},{"Id":6,"Name":"Rotationsjob"},{"Id":7,"Name":"Virksomhedspraktik"}],"EmploymentTypes":[{"Id":1,"Name":"Fastansættelse"},{"Id":16,"Name":"Tidsbegrænset ansættelse"}],"WorkPlace":{"Name":"Region Midtjylland","Address":{"AddressLine":"Strandvejen 24-26, Fjellerup","Country":{"Id":58,"Name":"Danmark"},"Municipality":{"Id":707,"Name":"Norddjurs"},"Region":{"Id":2,"Name":"Midtjylland"},"PostalCode":"8585","City":"Glesborg"},"PhoneNumber":{"Number":null,"Type":0,"Description":"Primary"},"FaxNumber":null,"Email":null,"WebAddress":null,"Description":null,"Logo":null,"WorkPlaceOrganizationNumber":"1003441545","OrganizationNumber":"29190925","OrganizationDescription":null},"JobPositionPosting":{"Id":5571817,"OriginalJppId":5571817,"HiringOrg":{"Name":"Region Midtjylland","Address":{"AddressLine":"Strandvejen 24-26, Fjellerup","Country":{"Id":58,"Name":"Danmark"},"Municipality":{"Id":707,"Name":"Norddjurs"},"Region":{"Id":2,"Name":"Midtjylland"},"PostalCode":"8585","City":"Glesborg"},"PhoneNumber":{"Number":null,"Type":0,"Description":"Primary"},"FaxNumber":null,"Email":null,"WebAddress":null,"Description":null,"Logo":null,"WorkPlaceOrganizationNumber":"1003441545","OrganizationNumber":"29190925","OrganizationDescription":null},"RecruitingCompany":null,"PublicationStartDate":"2022-04-06T00:00:00","PublicationEndDate":"2022-05-25T00:00:00","JobPositionInformation":{"PositionTitle":"Vil du være med til at skabe Danmarks førende specialtilbud til udsatte børn og unge?","Purpose":"<em>Trives du med at s&aelig;tte trivsel og udvikling i centrum for dit arbejde ? Vil du underst&oslash;tte det enkelte barns mulighed for et meningsfuldt liv ? Og kan du skabe struktur og forudsigelighed for b&oslash;rn og unge med autisme, epilepsi og mental retardering ?</em><br><br>M&oslash;lleb&aelig;kken s&oslash;ger en engageret medarbejder, som br&aelig;nder for at g&oslash;re en forskel for vores b&oslash;rn og unge. Vi s&oslash;ger dig der er fagligt st&aelig;rk, altid arbejder anerkendende og som har noget p&aring; hjertet.<br><br><strong>Om dig:</strong><ul><li>Du kan v&aelig;re uddannet social og sundhedsassistent, p&aelig;dagog, p&aelig;dagogisk assistent, ergo- ,fysio- eller psykomotorisk terapeut</li><li>Du kan varetage specialp&aelig;dagogiske opgaver og personlig pleje</li><li>Du trives med samarbejde p&aring; tv&aelig;rs af faggrupper</li><li>Du bevarer roen i pressede situationer</li><li>Du er psykisk stabil og har overblik</li><li>Du arbejder m&aring;lrettet med dokumentation og delm&aring;lsarbejde</li><li>Du har k&oslash;rekort</li></ul><strong>Om os:</strong><br>M&oslash;lleb&aelig;kken er opdelt i 3 afdelinger. Slusen til b&oslash;rn i aflastning. Reden til vores bo gruppe med d&oslash;gnanbragte b&oslash;rn og Labyrinten, som er en sk&aelig;rmet enhed. Vi er 30 fastansatte, som arbejder i teams og samarbejder p&aring; tv&aelig;rs af afdelingerne.<br><br>Vores m&aring;lgruppe er b&oslash;rn og unge i alderen 4 &ndash; 17 &aring;r med mental retardering og betydelig p&aring;virkning af adf&aelig;rd.<br><br>M&oslash;lleb&aelig;kken er et specialiseret tilbud til udsatte b&oslash;rn og unge under Specialomr&aring;de B&oslash;rn og Unge i Region Midtjylland. SBU vil v&aelig;re Danmarks f&oslash;rende specialtilbud til b&oslash;rn og unge. Derfor v&aelig;gtes uddannelse, innovation og udvikling, s&aring; der sikres h&oslash;j kvalitet og specialisering i alle tilbud.<br><br><strong>Vi tilbyder:</strong><ul><li>Et st&aelig;rkt fagligt milj&oslash; med fokus p&aring; det, vi kan sammen</li><li>Grundig introduktion, opl&aelig;ring og intern mentorordning</li><li>Deltagelse i supervision, uddannelse, kurser</li><li>Dynamiske kollegaer og ledelse, der samarbejder ud fra Region Midtjyllands v&aelig;rdier: Dialog, Dygtighed, Dristighed.</li></ul><strong>Ans&oslash;gningsfrist:</strong><br>Vi holder ans&aelig;ttelsessamtaler l&oslash;bende og forbeholder os retten til at ans&aelig;tte inden ans&oslash;gningsfristens udl&oslash;b.<br><br>L&oslash;n- og ans&aelig;ttelsesforhold efter g&aelig;ldende overenskomst mellem den forhandlingsberettigede organisation og Danske Regioner.<br><br><strong>Arbejdstid:</strong><br>Vi arbejder prim&aelig;rt aften og weekend. Arbejdstiden best&aring;r af weekendarbejde hver anden weekend i kombination med dag- og aftenarbejde p&aring; hverdage. Der er mulighed for, at arbejde dobbelte tjenester, hvorved flere frid&oslash;gn opn&aring;s.<br>&nbsp;<br>Der er fleksibilitet i arbejdsplanl&aelig;gningen og vi bestr&aelig;ber os p&aring; at im&oslash;dekomme dine &oslash;nsker.<br><br><strong>Kontakt:</strong><br>For yderligere oplysninger er du velkommen til at kontakte p&aelig;dagogisk teamleder Jeppe van der Burg, tlf.: 30 51 22 63 mandag til fredag kl. 8 &ndash; 15.<br><br><br><em>Stillingen er som udgangspunkt en fuldtidsstilling.</em><br><br><em>Da Region Midtjylland l&oslash;bende gennemf&oslash;rer besparelser og omorganiseringer, vil medarbejdere i omplacering, der s&oslash;ger stillingen, have fortrinsret til samtale.</em><br><br>","WorkLocation":{"AddressLine":"Strandvejen 24-26, Fjellerup","Country":{"Id":58,"Name":"Danmark"},"Municipality":{"Id":707,"Name":"Norddjurs"},"Region":{"Id":2,"Name":"Midtjylland"},"PostalCode":"8585","City":"Glesborg"},"EmploymentType":1,"WeeklyWorkHours":{"TypeId":1,"TypeName":"Fuldtid","Description":null},"CompensationDescription":null,"NumberToFill":1,"DriverLicense":[{"DriversLicenceType":3,"Name":"B","Description":"Almindelig bil"}],"Occupation":{"DiscoWeb":0,"AlternateNames":[],"GroupId":0,"AreaId":0,"Id":0,"Name":null},"IsGovernmentHiring":false,"JppContacts":[{"Id":7887667,"Email":null,"FaxNumber":null,"PersonName":"Jeppe van der Burg","FirstName":"Jeppe","LastName":"van der Burg","PositionTitle":null,"PhoneNumbers":[{"Number":"30512263","Type":2,"Description":"Mobil"}]}],"EmploymentDate":"2022-06-01T00:00:00"},"IsRecruitmentOfForeignNationals":false,"IsWorkInDenmark":false,"IsAnonymousEmployer":false,"IsDisabilityFriendly":false,"JppType":4,"ApplicationDetails":{"WorkHourMax":null,"WorkHourMin":null,"DailyWorkTimeWeekend":false,"DailyWorkTimeNight":false,"DailyWorkTimeEvening":false,"DailyWorkTimeDay":false,"ReferenceText":null,"RemarksToApplicant":null,"ByEmail":null,"ByPhone":null,"ApplyViaUrl":"https://rm.emply.net/recruitment/vacancyApply.aspx?publishingId=dd26f432-41ac-47e6-8d0b-933d3add95a1","ReplyInWriting":false,"ApplicationDeadlineDate":"2022-05-25T00:00:00"},"ContactAuthorityPhoneNumber":{"Number":null,"Type":0,"Description":"Primary"},"Status":7},"LogoUrl":"/CV/FindWork/GetLogo?JobAdId=5571817&Organisation=29190925","Address":"Strandvejen 24-26, Fjellerup,8585, Glesborg","ShowMap":true,"ShowShareButtonJobLog":false,"JobLogUrl":"/CV/Jobseeking/JobLog/CreateJobSearch?JobnetJobPostingIdentifier=5571817&Company.Name=Region Midtjylland&SubmissionDeadlineDate=2022-5-25&Title=Vil du være med til at skabe Danmarks førende specialtilbud til udsatte børn og unge?&WeeklyWorkTime=1","JobLogTemplateModel":{"Identifier":"00000000-0000-0000-0000-000000000000","UseWorkPlaceAddressForJoblog":false,"Category":0,"CvCustomerIdentifier":null,"JobSeekingStatus":null,"Title":"Vil du være med til at skabe Danmarks førende specialtilbud til udsatte børn og unge?","IsApplicationSourceRequired":true,"ApplicationSource":null,"IsWeeklyWorkTimeRequired":true,"WeeklyWorkTime":1,"HoursPerWeek":null,"JobnetJobPostingIdentifier":"5571817","JobAdDocument":{"Title":null,"Identifier":null,"IsDeletedBySystem":false,"IsDeletedByUser":false},"JobAdFile":null,"Company":{"JobLogEntryCategory":0,"ShowAddressFieldsEvenIfEmpty":false,"Name":"Region Midtjylland","Address":"Strandvejen 24-26, Fjellerup","Country":null,"EmploymentAreaID":null,"PostCode":"8585","IsCountryAndTownAndPostCodeEmpty":false,"IsTownAndPostCodeEmpty":false,"IsCountryDanmark":false,"Town":"Glesborg","ContactPerson":"Jeppe van der Burg","Phone":"30512263","Email":null,"Latitude":null,"Longitude":null,"DailyTravelTimeInMinutes":null,"DistanceToCompanyInMeters":null,"IsCreateMode":false},"TypeOfSubmission":null,"SubmissionDate":"2022-05-25T00:00:00","SubmissionDateFormatted":null,"SubmissionDateTiks":0,"IsSubmissionDateRequired":false,"Status":0,"DateCreatedFormatted":null,"DateCreated":null,"DateModifiedFormatted":null,"DateModified":null,"LastModifiedDateTiks":0,"DateClosed":null,"JobApplicationDocument":{"Title":null,"Identifier":null,"IsDeletedBySystem":false,"IsDeletedByUser":false},"CvDocument":{"Title":null,"Identifier":null,"IsDeletedBySystem":false,"IsDeletedByUser":false},"JobApplicationFile":null,"CvFile":null,"SubmissionDeadlineDate":null,"IsPersisted":false,"ServerValidationErrors":[],"HasServerValidationErrors":false},"JoblogWorkTime":{"WorkHour":null,"DailyWorkTime":null},"Place":"Arbejdspladsen ligger i Norddjurs kommune","OpenPrintDialog":false,"WorkPlaceInfoText":"Region Midtjylland","JobCenterContactDetails":"","WorkPlaceDescriptionText":null,"FavoriteText":"","IsFavorite":false,"ShowFavorite":false,"MetaOgTextForSharing":"Trives du med at s&aelig;tte trivsel og udvikling i centrum for dit arbejde ? Vil du underst&oslash;tte det enkelte barns mulighed for et meningsfuldt liv ? Og kan du skabe struktur og forudsigelighed for b&oslash;rn og unge med autisme, epilepsi og mental retardering ?M&oslash;lleb&aelig;kken s&oslash;ger en engageret medarbejder, som br&aelig;nde","DescriptionForSharing":"\"Trives du med at s\\u0026aelig;tte trivsel og udvikling i centrum for dit arbejde ? Vil du underst\\u0026oslash;tte det enkelte barns mulighed for et meningsfuldt liv ? Og kan du skabe struktur og forudsigelighed for b\\u0026oslash;rn og unge med autisme, epilepsi og mental retardering ?M\\u0026oslash;lleb\\u0026aelig;kken s\\u0026oslash;ger en engageret medarbejder, som br\\u0026aelig;nde\"","TitleForSharing":"\"Vil du være med til at skabe Danmarks førende specialtilbud til udsatte børn og unge?\"","RutePlan":"https://www.google.dk/maps/dir//Strandvejen+24-26,+Fjellerup,8585,+Glesborg/","FormattedPurpose":"<em>Trives du med at s&aelig;tte trivsel og udvikling i centrum for dit arbejde ? Vil du underst&oslash;tte det enkelte barns mulighed for et meningsfuldt liv ? Og kan du skabe struktur og forudsigelighed for b&oslash;rn og unge med autisme, epilepsi og mental retardering ?</em><br><br>M&oslash;lleb&aelig;kken s&oslash;ger en engageret medarbejder, som br&aelig;nder for at g&oslash;re en forskel for vores b&oslash;rn og unge. Vi s&oslash;ger dig der er fagligt st&aelig;rk, altid arbejder anerkendende og som har noget p&aring; hjertet.<br><br><strong>Om dig:</strong><ul><li>Du kan v&aelig;re uddannet social og sundhedsassistent, p&aelig;dagog, p&aelig;dagogisk assistent, ergo- ,fysio- eller psykomotorisk terapeut</li><li>Du kan varetage specialp&aelig;dagogiske opgaver og personlig pleje</li><li>Du trives med samarbejde p&aring; tv&aelig;rs af faggrupper</li><li>Du bevarer roen i pressede situationer</li><li>Du er psykisk stabil og har overblik</li><li>Du arbejder m&aring;lrettet med dokumentation og delm&aring;lsarbejde</li><li>Du har k&oslash;rekort</li></ul><strong>Om os:</strong><br>M&oslash;lleb&aelig;kken er opdelt i 3 afdelinger. Slusen til b&oslash;rn i aflastning. Reden til vores bo gruppe med d&oslash;gnanbragte b&oslash;rn og Labyrinten, som er en sk&aelig;rmet enhed. Vi er 30 fastansatte, som arbejder i teams og samarbejder p&aring; tv&aelig;rs af afdelingerne.<br><br>Vores m&aring;lgruppe er b&oslash;rn og unge i alderen 4 &ndash; 17 &aring;r med mental retardering og betydelig p&aring;virkning af adf&aelig;rd.<br><br>M&oslash;lleb&aelig;kken er et specialiseret tilbud til udsatte b&oslash;rn og unge under Specialomr&aring;de B&oslash;rn og Unge i Region Midtjylland. SBU vil v&aelig;re Danmarks f&oslash;rende specialtilbud til b&oslash;rn og unge. Derfor v&aelig;gtes uddannelse, innovation og udvikling, s&aring; der sikres h&oslash;j kvalitet og specialisering i alle tilbud.<br><br><strong>Vi tilbyder:</strong><ul><li>Et st&aelig;rkt fagligt milj&oslash; med fokus p&aring; det, vi kan sammen</li><li>Grundig introduktion, opl&aelig;ring og intern mentorordning</li><li>Deltagelse i supervision, uddannelse, kurser</li><li>Dynamiske kollegaer og ledelse, der samarbejder ud fra Region Midtjyllands v&aelig;rdier: Dialog, Dygtighed, Dristighed.</li></ul><strong>Ans&oslash;gningsfrist:</strong><br>Vi holder ans&aelig;ttelsessamtaler l&oslash;bende og forbeholder os retten til at ans&aelig;tte inden ans&oslash;gningsfristens udl&oslash;b.<br><br>L&oslash;n- og ans&aelig;ttelsesforhold efter g&aelig;ldende overenskomst mellem den forhandlingsberettigede organisation og Danske Regioner.<br><br><strong>Arbejdstid:</strong><br>Vi arbejder prim&aelig;rt aften og weekend. Arbejdstiden best&aring;r af weekendarbejde hver anden weekend i kombination med dag- og aftenarbejde p&aring; hverdage. Der er mulighed for, at arbejde dobbelte tjenester, hvorved flere frid&oslash;gn opn&aring;s.<br> <br>Der er fleksibilitet i arbejdsplanl&aelig;gningen og vi bestr&aelig;ber os p&aring; at im&oslash;dekomme dine &oslash;nsker.<br><br><strong>Kontakt:</strong><br>For yderligere oplysninger er du velkommen til at kontakte p&aelig;dagogisk teamleder Jeppe van der Burg, tlf.: 30 51 22 63 mandag til fredag kl. 8 &ndash; 15.<br><br><br><em>Stillingen er som udgangspunkt en fuldtidsstilling.</em><br><br><em>Da Region Midtjylland l&oslash;bende gennemf&oslash;rer besparelser og omorganiseringer, vil medarbejdere i omplacering, der s&oslash;ger stillingen, have fortrinsret til samtale.</em><br><br>","MapUrl":"https://www.google.dk/maps/place/Strandvejen+24-26,+Fjellerup,8585,+Glesborg/","OrganizationNumber":"29190925","ShowSearchJobButton":false,"ShowPrint":false,"BackToFindWorkButtonUrl":null},"isExternal":false}