{"summary":{"AutomatchType":0,"Abroad":false,"Weight":1,"Title":"Engageret IT-servicemanager til Lægemiddelstyrelsen","JobHeadline":"Engageret IT-servicemanager til Lægemiddelstyrelsen","Presentation":"Vi mangler en kollega, som ser sig selv som et naturligt bindeled mellem vores leverandører og Lægemiddelstyrelsen. En person med systematisk tilgang til tingene, som elsker at tage ansvar for os ","HiringOrgName":"Lægemiddelstyrelsen","WorkPlaceAddress":"Axel Heides Gade 1","WorkPlacePostalCode":"2300","WorkPlaceCity":"København S","WorkPlaceOtherAddress":false,"WorkPlaceAbroad":false,"WorkPlaceNotStatic":false,"UseWorkPlaceAddressForJoblog":true,"PostingCreated":"2022-04-29T00:00:00","LastDateApplication":"2022-05-22T00:00:00","FormattedLastDateApplication":"22. maj 2022","AssignmentStartDate":"0001-01-01T00:00:00","IsHotjob":false,"IsExternal":false,"Url":"https://job.jobnet.dk/CV/FindWork/Details/5587162","Region":"Hovedstaden og Bornholm","Municipality":"København","Country":"Danmark","PostalCode":"2300","PostalCodeName":null,"JobAnnouncementType":"","EmploymentType":"","WorkHours":"Fuldtid","OccupationArea":"Akademisk arbejde","OccupationGroup":"Administrativt arbejde","Occupation":"Fuldmægtig","Location":{"Latitude":55.6614,"Longitude":12.57},"JoblogWorkTime":{"WorkHour":null,"DailyWorkTime":null},"WorkplaceID":117262,"OrganisationId":"104409","HiringOrgCVR":37052485,"UserLoggedIn":false,"AnonymousEmployer":false,"ShareUrl":"https://job.jobnet.dk/CV/FindWork/DetailsSocialmedia/5587162","DetailsUrl":"https://job.jobnet.dk/CV/FindWork/Details/5587162","JobLogUrl":"https://job.jobnet.dk/CV/FindWork/Details/5587162","HasLocationValues":true,"ID":"5587162","Latitude":55.6614,"Longitude":12.57},"details":{"WorkSchedule":[{"Id":1,"Name":"Fuldtid"},{"Id":16,"Name":"Deltid"}],"WorkConditions":[{"Id":1,"Name":"Almindelige vilkår"},{"Id":2,"Name":"Fleksjob"},{"Id":3,"Name":"Skånejob"},{"Id":4,"Name":"Egnet til efterlønnere og seniorer"},{"Id":5,"Name":"Job med løntilskud"},{"Id":6,"Name":"Rotationsjob"},{"Id":7,"Name":"Virksomhedspraktik"}],"EmploymentTypes":[{"Id":1,"Name":"Fastansættelse"},{"Id":16,"Name":"Tidsbegrænset ansættelse"}],"WorkPlace":{"Name":"Lægemiddelstyrelsen","Address":{"AddressLine":"Axel Heides Gade 1","Country":{"Id":58,"Name":"Danmark"},"Municipality":{"Id":101,"Name":"København"},"Region":{"Id":4,"Name":"Hovedstaden, Sjælland og Bornholm"},"PostalCode":"2300","City":"København S"},"PhoneNumber":{"Number":"41235901","Type":0,"Description":"Primary"},"FaxNumber":null,"Email":null,"WebAddress":null,"Description":null,"Logo":117262,"WorkPlaceOrganizationNumber":"1020691286","OrganizationNumber":"37052485","OrganizationDescription":null},"JobPositionPosting":{"Id":5587162,"OriginalJppId":5587162,"HiringOrg":{"Name":"Lægemiddelstyrelsen","Address":{"AddressLine":"Axel Heides Gade 1","Country":{"Id":58,"Name":"Danmark"},"Municipality":{"Id":101,"Name":"København"},"Region":{"Id":4,"Name":"Hovedstaden, Sjælland og Bornholm"},"PostalCode":"2300","City":"København S"},"PhoneNumber":{"Number":"41235901","Type":0,"Description":"Primary"},"FaxNumber":null,"Email":null,"WebAddress":null,"Description":null,"Logo":117262,"WorkPlaceOrganizationNumber":"1020691286","OrganizationNumber":"37052485","OrganizationDescription":null},"RecruitingCompany":null,"PublicationStartDate":"2022-04-29T00:00:00","PublicationEndDate":"2022-05-22T00:00:00","JobPositionInformation":{"PositionTitle":"Engageret IT-servicemanager til Lægemiddelstyrelsen","Purpose":"<em>Vi mangler en kollega, som ser sig selv som et naturligt bindeled mellem vores leverandører og Lægemiddelstyrelsen. En person med systematisk tilgang til tingene, som elsker at tage ansvar for os alle og leverandørstyre vores leverandører på en god måde, så også de ser værdi i at samarbejde med os.</em><br><br>  <em>Du skal have mod på at bidrage til at realisere vores interessante og ambitiøse strategi og sammen med gode kollegaer på tværs af Lægemiddelstyrelsen sikre stabil drift og et godt samarbejdsklima mellem Lægemiddelstyrelsen og vores leverandører.  </em><br><br>  <strong>Om Lægemiddelstyrelsen</strong><br /> Vi arbejder i Lægemiddelstyrelsen hver dag sammen, om at sikre sikker og effektiv medicin og medicinsk udstyr til gavn for borgere, virksomheder og samarbejdspartnerne i EU.<br><br>  Vi har høje ambitioner om at være en fantastisk arbejdsplads, hvor fokus er på at alle bidrager med deres unikke kompetencer, og hvor vi også har det sjovt sammen. Vi sætter udvikling af dig og dine kollegaer højt, og et socialt godt kollegaskab er vigtigt for os.<br><br>  <strong>Om IT & Digital Transformation</strong><br /> Du bliver en del af fællesskabet i IT & Digital Transformation, som er det helt centrale bindeled mellem vores leverandører, som udvikler og drifter vores IT-løsninger, og vores kollegaer i resten af styrelsen, som er brugere af vores fælles udarbejdede IT-løsninger.<br><br>  IT & Digital Transformation består af styrelsens IT-chef og 24 kollegaer fordelt i to sektioner og et team. Vi arbejder tæt sammen i enheden og lægger stor vægt på, at vi sammen hele tiden udvikler os dynamisk i takt med de nye tekniske muligheder og krav fra omverdenen.<br><br>  Vi har en høj faglighed og til sammen mange års erfaring i Lægemiddelstyrelsen, som vi dagligt bringer i spil for at løfte vores opgaver - og vi glæder os til, at dine erfaringer og kompetencer og din måde at se tingene på kan gøre os endnu bedre.<br><br>  <strong>Din hverdag hos os</strong><br /> Du bliver ansat i sektionen Projekter & Driftsstyring, der løfter ansvaret for både IT-projekter, tekniske opgraderinger og sikring af den daglige drift sammen med vores IT-leverandører og vores kollegaer i resten af styrelsen. Dine kollegaer har mange forskellige fagligheder, og du vil få en rigtig god indsigt i hele læge­middelområdet, der blandt andet senest har spillet en vigtig samfundskritisk rolle i sikring af COVID-19 vacciner til alle borgere.<br><br>  Vi er ved at indgå en ny vedligeholdelseskontrakt, som dækker over hovedparten af vores systemer, og hvor vi mangler dig til dels at etablere relationer og aftale samarbejdsformer til gavn for begge parter, dels sikre at aftalens krav efterfølgende overholdes. På samme måde vil du blive ansvarlig for vores driftskontrakt, som vedrører al drift i Lægemiddelstyrelsen, der er outsourcet til en ekstern leverandør.<br><br>  Lægemiddelstyrelsens IT-landskab er omfattende og kompleks med mange spændende udfordringer. Vi er netop nu i samarbejde med vores IT-leverandører ved at sikre en transformation fra vores ældre special­udviklede systemer til et øget brug af standardløsninger og moderne teknologi. Derudover kigger vi ind i løbende implementering af Microsoft 365, så det understøtter forretningens behov bedst muligt fremadrettet.<br /> <br /> Dine primære opgaver vil alt efter dine kompetencer og i samarbejde med dine kollegaer blandt andet være:<br><br>  <ul> \t<li>at medvirke til at sikre roller og ansvar, governance og processer i vores nye vedligeholdelses­kontrakt. Dette skal ske i tæt samarbejde med projektet, som arbejder med udbud og kontraktind­gåelse, leverandøren og dine øvrige kollegaer</li> \t<li>at være ansvarlig for efterfølgende at sikre efterlevelse af vedligeholdelseskontrakten - igen i tæt samarbejde med leverandøren. Denne opgave skal udføres tværgående i IT & Digital Transformation og i Lægemid­del­styrelsen med opfølgning på baggrund af månedlige skriftlige rapporter, herunder månedlige vederlag fra vores leverandør, estimatproces på nye forretningskomponenter og større vedligehold</li> \t<li>på samme måde at være ansvarlig for at sikre efterlevelse af vores nuværende og kommende driftskontrakt</li> \t<li>at foreslå og implementere løbende forbedringer samt opdatere og vedligeholde kontrakter og de aftalehåndbøger, der præciserer aftalerne i kontrakterne</li> \t<li>foretage benchmarks.</li> </ul>  Du bliver koordinator på en række opgaver og vil komme til at arbejde tæt sammen med dine kollegaer både i IT & Digital Transformation og i resten af Lægemiddelstyrelsen. Du vil også komme til at indgå i en vigtig rolle i løsningen af mange forskelligartede opgaver i sektionen, herunder at understøtte IT-projekter, informa­tions­sikkerhed og kvalitetsarbejdet.<br><br>  Vi arbejder med stort medarbejderansvar. Det forventes man i høj grad selv kan planlægge sine opgaver, og dine opgaver vil blive baseret på dine interesser og kompetencer.<br><br>  <strong>Din uddannelse, erfaring og personlige kompetencer</strong><br /> Det vigtigste er, at du har en stor lyst til at arbejde med og forbedre vores samarbejde med leverandørerne til gavn for både Lægemiddelstyrelsen og leverandørerne.<br><br>  Samarbejde, tillid og dialog er vigtigst, derfor forventes det, at du har:<br><br>  <ul> \t<li>personligt drive og positiv energi</li> \t<li>gode evner indenfor samarbejde og kommunikation, og vi lægger vægt på, at du formår at forhandle og at gå foran i koordineringen og opfølgningen på opgaverne samt sikre leverandøren de bedste betingelser for, at de kan indfri deres del af samarbejdet bedst muligt</li> \t<li>evnen til at være systematisk i din opfølgning, og at du arbejder struktureret og proaktivt kommer med løsninger</li> \t<li>lyst til konstruktivt samarbejde både med dine kollegaer i IT & Digital Transformation og med resten af Lægemiddelstyrelsen.</li> </ul>  Derudover er det en fordel, hvis du har:<br><br>  <ul> \t<li>erfaring med IT-servicemanagement og IT-leverandørsamarbejde</li> \t<li>en relevant akademisk uddannelse</li> \t<li>erfaring med ITIL</li> \t<li>gode analytiske evner og proceskompetencer.</li> </ul>  <strong>Vi tilbyder</strong><br /> Hos os får du et meningsfyldt og fagligt udfordrende arbejde, hvor du i stærkt kollegaskab bidrager til at skabe bedre sundhed for alle. Du vil med garanti blive udfordret i et tværfagligt miljø, hvor du får mulighed for at anvende og udvikle dine kompetencer inden for et bredt felt af arbejdsopgaver. Vi sidder i et storrums­kontor og vores arbejdsklima er energisk, uformelt og præget af stort fagligt engagement og gensidig respekt – og med plads til grin, men også til fejl, som vi sammen lærer af. <br><br>  <strong>Om ansættelsen</strong><br /> Afhængig af din uddannelsesmæssige baggrund bliver du ansat efter gældende overenskomst mellem Finansministeriet og Akademikernes Centralorganisation eller som it-medarbejder efter gældende overenskomst mellem Finansministeriet og Offentligt Ansattes Organisationer (OAO-S-fællesoverenskomsten) og gældende organisationsaftale mellem Finansministeriet og HK/Stat for kontorfunktionærer, laboranter og it-medarbejdere (HK), jf. aftalens bestemmelser vedrørende it-medarbejdere.<br><br>  I Lægemiddelstyrelsen træffer vi afgørelser i myndighedssager, og derfor er det vigtigt for os, at der ikke kan stilles spørgsmålstegn ved vores habilitet. Derfor er det en forudsætning for ansættelse i Lægemiddelstyrelsen, at du ikke ejer aktier, anparter, andele eller lignende i en lægemiddel- og/eller medicovirksomhed. Ejer du i dag såkaldte medarbejderaktier i en lægemiddel- og/eller medicovirksomhed, har du dog en vis periode til at afhænde disse aktier.<br><br>  <strong>Kontakt os gerne</strong><br /> Du kan få mere at vide om stillingen ved at kontakte sektionsleder Sune Maaholm på telefon 41235901.<br /> <br /> Læs også vores IT-strategi og Lægemiddelstyrelsens samlede strategi på <a href=\"http://www.laegemiddelstyrelsen.dk\" target=\"_blank\">www.laegemiddelstyrelsen.dk</a>.<br><br>  <strong>Er du interesseret?  </strong><br /> Klik på ”søg stillingen” og send os din ansøgning med CV og eksamensbevis. Ansættelsessamtaler forventes afholdt fra uge 21. Der kan indgå test i ansættelsesforløbet.<br><br>","WorkLocation":{"AddressLine":"Axel Heides Gade 1","Country":{"Id":58,"Name":"Danmark"},"Municipality":{"Id":101,"Name":"København"},"Region":{"Id":4,"Name":"Hovedstaden, Sjælland og Bornholm"},"PostalCode":"2300","City":"København S"},"EmploymentType":1,"WeeklyWorkHours":{"TypeId":1,"TypeName":"Fuldtid","Description":null},"CompensationDescription":null,"NumberToFill":1,"DriverLicense":[],"Occupation":{"DiscoWeb":0,"AlternateNames":[],"GroupId":0,"AreaId":0,"Id":0,"Name":null},"IsGovernmentHiring":false,"JppContacts":[{"Id":7946286,"Email":null,"FaxNumber":null,"PersonName":"Sune Maaholm","FirstName":"Sune","LastName":"Maaholm","PositionTitle":null,"PhoneNumbers":[{"Number":"41235901","Type":0,"Description":"Hovednummer"}]}],"EmploymentDate":"2022-08-01T00:00:00"},"IsRecruitmentOfForeignNationals":false,"IsWorkInDenmark":false,"IsAnonymousEmployer":false,"IsDisabilityFriendly":false,"JppType":4,"ApplicationDetails":{"WorkHourMax":null,"WorkHourMin":null,"DailyWorkTimeWeekend":false,"DailyWorkTimeNight":false,"DailyWorkTimeEvening":false,"DailyWorkTimeDay":false,"ReferenceText":null,"RemarksToApplicant":null,"ByEmail":null,"ByPhone":null,"ApplyViaUrl":"https://candidate.hr-manager.net/ApplicationInit.aspx?cid=5001&ProjectId=155762&DepartmentId=9910&MediaId=2505&SkipAdvertisement=true","ReplyInWriting":false,"ApplicationDeadlineDate":"2022-05-22T00:00:00"},"ContactAuthorityPhoneNumber":{"Number":null,"Type":0,"Description":"Primary"},"Status":7},"LogoUrl":"/CV/FindWork/GetLogo?JobAdId=5587162&WorkPlace=117262&Organisation=37052485","Address":"Axel Heides Gade 1,2300, København S","ShowMap":true,"ShowShareButtonJobLog":false,"JobLogUrl":"/CV/Jobseeking/JobLog/CreateJobSearch?JobnetJobPostingIdentifier=5587162&Company.Name=Lægemiddelstyrelsen&SubmissionDeadlineDate=2022-5-22&Title=Engageret IT-servicemanager til Lægemiddelstyrelsen&WeeklyWorkTime=1","JobLogTemplateModel":{"Identifier":"00000000-0000-0000-0000-000000000000","UseWorkPlaceAddressForJoblog":false,"Category":0,"CvCustomerIdentifier":null,"JobSeekingStatus":null,"Title":"Engageret IT-servicemanager til Lægemiddelstyrelsen","IsApplicationSourceRequired":true,"ApplicationSource":null,"IsWeeklyWorkTimeRequired":true,"WeeklyWorkTime":1,"HoursPerWeek":null,"JobnetJobPostingIdentifier":"5587162","JobAdDocument":{"Title":null,"Identifier":null,"IsDeletedBySystem":false,"IsDeletedByUser":false},"JobAdFile":null,"Company":{"JobLogEntryCategory":0,"ShowAddressFieldsEvenIfEmpty":false,"Name":"Lægemiddelstyrelsen","Address":"Axel Heides Gade 1","Country":null,"EmploymentAreaID":null,"PostCode":"2300","IsCountryAndTownAndPostCodeEmpty":false,"IsTownAndPostCodeEmpty":false,"IsCountryDanmark":false,"Town":"København S","ContactPerson":"Sune Maaholm","Phone":"41235901","Email":null,"Latitude":null,"Longitude":null,"DailyTravelTimeInMinutes":null,"DistanceToCompanyInMeters":null,"IsCreateMode":false},"TypeOfSubmission":null,"SubmissionDate":"2022-05-22T00:00:00","SubmissionDateFormatted":null,"SubmissionDateTiks":0,"IsSubmissionDateRequired":false,"Status":0,"DateCreatedFormatted":null,"DateCreated":null,"DateModifiedFormatted":null,"DateModified":null,"LastModifiedDateTiks":0,"DateClosed":null,"JobApplicationDocument":{"Title":null,"Identifier":null,"IsDeletedBySystem":false,"IsDeletedByUser":false},"CvDocument":{"Title":null,"Identifier":null,"IsDeletedBySystem":false,"IsDeletedByUser":false},"JobApplicationFile":null,"CvFile":null,"SubmissionDeadlineDate":null,"IsPersisted":false,"ServerValidationErrors":[],"HasServerValidationErrors":false},"JoblogWorkTime":{"WorkHour":null,"DailyWorkTime":null},"Place":"Arbejdspladsen ligger i København kommune","OpenPrintDialog":false,"WorkPlaceInfoText":"Lægemiddelstyrelsen","JobCenterContactDetails":"","WorkPlaceDescriptionText":null,"FavoriteText":"","IsFavorite":false,"ShowFavorite":false,"MetaOgTextForSharing":"Vi mangler en kollega, som ser sig selv som et naturligt bindeled mellem vores leverandører og Lægemiddelstyrelsen. En person med systematisk tilgang til tingene, som elsker at tage ansvar for os alle og leverandørstyre vores leverandører på en god måde, så også de ser værdi i at samarbejde med os.  Du skal have mod på at bidrage til at realisere v","DescriptionForSharing":"\"Vi mangler en kollega, som ser sig selv som et naturligt bindeled mellem vores leverandører og Lægemiddelstyrelsen. En person med systematisk tilgang til tingene, som elsker at tage ansvar for os alle og leverandørstyre vores leverandører på en god måde, så også de ser værdi i at samarbejde med os.  Du skal have mod på at bidrage til at realisere v\"","TitleForSharing":"\"Engageret IT-servicemanager til Lægemiddelstyrelsen\"","RutePlan":"https://www.google.dk/maps/dir//Axel+Heides+Gade+1,2300,+København+S/","FormattedPurpose":"<em>Vi mangler en kollega, som ser sig selv som et naturligt bindeled mellem vores leverandører og Lægemiddelstyrelsen. En person med systematisk tilgang til tingene, som elsker at tage ansvar for os alle og leverandørstyre vores leverandører på en god måde, så også de ser værdi i at samarbejde med os.</em><br><br>  <em>Du skal have mod på at bidrage til at realisere vores interessante og ambitiøse strategi og sammen med gode kollegaer på tværs af Lægemiddelstyrelsen sikre stabil drift og et godt samarbejdsklima mellem Lægemiddelstyrelsen og vores leverandører.  </em><br><br>  <strong>Om Lægemiddelstyrelsen</strong><br /> Vi arbejder i Lægemiddelstyrelsen hver dag sammen, om at sikre sikker og effektiv medicin og medicinsk udstyr til gavn for borgere, virksomheder og samarbejdspartnerne i EU.<br><br>  Vi har høje ambitioner om at være en fantastisk arbejdsplads, hvor fokus er på at alle bidrager med deres unikke kompetencer, og hvor vi også har det sjovt sammen. Vi sætter udvikling af dig og dine kollegaer højt, og et socialt godt kollegaskab er vigtigt for os.<br><br>  <strong>Om IT & Digital Transformation</strong><br /> Du bliver en del af fællesskabet i IT & Digital Transformation, som er det helt centrale bindeled mellem vores leverandører, som udvikler og drifter vores IT-løsninger, og vores kollegaer i resten af styrelsen, som er brugere af vores fælles udarbejdede IT-løsninger.<br><br>  IT & Digital Transformation består af styrelsens IT-chef og 24 kollegaer fordelt i to sektioner og et team. Vi arbejder tæt sammen i enheden og lægger stor vægt på, at vi sammen hele tiden udvikler os dynamisk i takt med de nye tekniske muligheder og krav fra omverdenen.<br><br>  Vi har en høj faglighed og til sammen mange års erfaring i Lægemiddelstyrelsen, som vi dagligt bringer i spil for at løfte vores opgaver - og vi glæder os til, at dine erfaringer og kompetencer og din måde at se tingene på kan gøre os endnu bedre.<br><br>  <strong>Din hverdag hos os</strong><br /> Du bliver ansat i sektionen Projekter & Driftsstyring, der løfter ansvaret for både IT-projekter, tekniske opgraderinger og sikring af den daglige drift sammen med vores IT-leverandører og vores kollegaer i resten af styrelsen. Dine kollegaer har mange forskellige fagligheder, og du vil få en rigtig god indsigt i hele læge­middelområdet, der blandt andet senest har spillet en vigtig samfundskritisk rolle i sikring af COVID-19 vacciner til alle borgere.<br><br>  Vi er ved at indgå en ny vedligeholdelseskontrakt, som dækker over hovedparten af vores systemer, og hvor vi mangler dig til dels at etablere relationer og aftale samarbejdsformer til gavn for begge parter, dels sikre at aftalens krav efterfølgende overholdes. På samme måde vil du blive ansvarlig for vores driftskontrakt, som vedrører al drift i Lægemiddelstyrelsen, der er outsourcet til en ekstern leverandør.<br><br>  Lægemiddelstyrelsens IT-landskab er omfattende og kompleks med mange spændende udfordringer. Vi er netop nu i samarbejde med vores IT-leverandører ved at sikre en transformation fra vores ældre special­udviklede systemer til et øget brug af standardløsninger og moderne teknologi. Derudover kigger vi ind i løbende implementering af Microsoft 365, så det understøtter forretningens behov bedst muligt fremadrettet.<br /> <br /> Dine primære opgaver vil alt efter dine kompetencer og i samarbejde med dine kollegaer blandt andet være:<br><br>  <ul> \t<li>at medvirke til at sikre roller og ansvar, governance og processer i vores nye vedligeholdelses­kontrakt. Dette skal ske i tæt samarbejde med projektet, som arbejder med udbud og kontraktind­gåelse, leverandøren og dine øvrige kollegaer</li> \t<li>at være ansvarlig for efterfølgende at sikre efterlevelse af vedligeholdelseskontrakten - igen i tæt samarbejde med leverandøren. Denne opgave skal udføres tværgående i IT & Digital Transformation og i Lægemid­del­styrelsen med opfølgning på baggrund af månedlige skriftlige rapporter, herunder månedlige vederlag fra vores leverandør, estimatproces på nye forretningskomponenter og større vedligehold</li> \t<li>på samme måde at være ansvarlig for at sikre efterlevelse af vores nuværende og kommende driftskontrakt</li> \t<li>at foreslå og implementere løbende forbedringer samt opdatere og vedligeholde kontrakter og de aftalehåndbøger, der præciserer aftalerne i kontrakterne</li> \t<li>foretage benchmarks.</li> </ul>  Du bliver koordinator på en række opgaver og vil komme til at arbejde tæt sammen med dine kollegaer både i IT & Digital Transformation og i resten af Lægemiddelstyrelsen. Du vil også komme til at indgå i en vigtig rolle i løsningen af mange forskelligartede opgaver i sektionen, herunder at understøtte IT-projekter, informa­tions­sikkerhed og kvalitetsarbejdet.<br><br>  Vi arbejder med stort medarbejderansvar. Det forventes man i høj grad selv kan planlægge sine opgaver, og dine opgaver vil blive baseret på dine interesser og kompetencer.<br><br>  <strong>Din uddannelse, erfaring og personlige kompetencer</strong><br /> Det vigtigste er, at du har en stor lyst til at arbejde med og forbedre vores samarbejde med leverandørerne til gavn for både Lægemiddelstyrelsen og leverandørerne.<br><br>  Samarbejde, tillid og dialog er vigtigst, derfor forventes det, at du har:<br><br>  <ul> \t<li>personligt drive og positiv energi</li> \t<li>gode evner indenfor samarbejde og kommunikation, og vi lægger vægt på, at du formår at forhandle og at gå foran i koordineringen og opfølgningen på opgaverne samt sikre leverandøren de bedste betingelser for, at de kan indfri deres del af samarbejdet bedst muligt</li> \t<li>evnen til at være systematisk i din opfølgning, og at du arbejder struktureret og proaktivt kommer med løsninger</li> \t<li>lyst til konstruktivt samarbejde både med dine kollegaer i IT & Digital Transformation og med resten af Lægemiddelstyrelsen.</li> </ul>  Derudover er det en fordel, hvis du har:<br><br>  <ul> \t<li>erfaring med IT-servicemanagement og IT-leverandørsamarbejde</li> \t<li>en relevant akademisk uddannelse</li> \t<li>erfaring med ITIL</li> \t<li>gode analytiske evner og proceskompetencer.</li> </ul>  <strong>Vi tilbyder</strong><br /> Hos os får du et meningsfyldt og fagligt udfordrende arbejde, hvor du i stærkt kollegaskab bidrager til at skabe bedre sundhed for alle. Du vil med garanti blive udfordret i et tværfagligt miljø, hvor du får mulighed for at anvende og udvikle dine kompetencer inden for et bredt felt af arbejdsopgaver. Vi sidder i et storrums­kontor og vores arbejdsklima er energisk, uformelt og præget af stort fagligt engagement og gensidig respekt – og med plads til grin, men også til fejl, som vi sammen lærer af. <br><br>  <strong>Om ansættelsen</strong><br /> Afhængig af din uddannelsesmæssige baggrund bliver du ansat efter gældende overenskomst mellem Finansministeriet og Akademikernes Centralorganisation eller som it-medarbejder efter gældende overenskomst mellem Finansministeriet og Offentligt Ansattes Organisationer (OAO-S-fællesoverenskomsten) og gældende organisationsaftale mellem Finansministeriet og HK/Stat for kontorfunktionærer, laboranter og it-medarbejdere (HK), jf. aftalens bestemmelser vedrørende it-medarbejdere.<br><br>  I Lægemiddelstyrelsen træffer vi afgørelser i myndighedssager, og derfor er det vigtigt for os, at der ikke kan stilles spørgsmålstegn ved vores habilitet. Derfor er det en forudsætning for ansættelse i Lægemiddelstyrelsen, at du ikke ejer aktier, anparter, andele eller lignende i en lægemiddel- og/eller medicovirksomhed. Ejer du i dag såkaldte medarbejderaktier i en lægemiddel- og/eller medicovirksomhed, har du dog en vis periode til at afhænde disse aktier.<br><br>  <strong>Kontakt os gerne</strong><br /> Du kan få mere at vide om stillingen ved at kontakte sektionsleder Sune Maaholm på telefon 41235901.<br /> <br /> Læs også vores IT-strategi og Lægemiddelstyrelsens samlede strategi på <a target=\"_blank\" href=\"http://www.laegemiddelstyrelsen.dk\" user-behavior-tracking=\"Contact\" user-behavior-tracking-id=\"5587162\">www.laegemiddelstyrelsen.dk</a>.<br><br>  <strong>Er du interesseret?  </strong><br /> Klik på ”søg stillingen” og send os din ansøgning med CV og eksamensbevis. Ansættelsessamtaler forventes afholdt fra uge 21. Der kan indgå test i ansættelsesforløbet.<br><br>","MapUrl":"https://www.google.dk/maps/place/Axel+Heides+Gade+1,2300,+København+S/","OrganizationNumber":"37052485","ShowSearchJobButton":false,"ShowPrint":false,"BackToFindWorkButtonUrl":null},"isExternal":false}